salesforce_reporting-0.1.3.dist-info/METADATA
salesforce_reporting-0.1.3.dist-info/DESCRIPTION.rst
salesforce_reporting-0.1.3.dist-info/metadata.json
salesforce_reporting-0.1.3.dist-info/top_level.txt
salesforce_reporting-0.1.3.dist-info/RECORD
salesforce_reporting-0.1.3.dist-info/WHEEL
salesforce_reporting/parsers.py
salesforce_reporting/__init__.py
salesforce_reporting/login.py
