Metadata-Version: 2.0
Name: salesforce-reporting
Version: 0.1.3
Summary: Get data from Salesforce reports with python
Home-page: https://github.com/cghall/salesforce-reporting
Author: Chris Hall
Author-email: chris@impactbox.co.uk
License: UNKNOWN
Keywords: python,salesforce,salesforce.com
Platform: UNKNOWN
Classifier: Programming Language :: Python :: 2
Classifier: Programming Language :: Python :: 3
Requires-Dist: requests
